{
  "about.friendlyLinks.subtitle": "Trang web và dịch vụ liên quan",
  "about.friendlyLinks.title": "Liên kết tình bạn",
  "about.hero.content": "Đại học Vũ Hán · Các khóa học và nền tảng điều hướng khuôn viên trường",
  "about.hero.title": "Sứ mệnh của chúng tôi",
  "about.philosophy.md": "# Mã nguồn mở\nĐược xây dựng bởi cộng đồng.",
  "about.team.title": "Đội ngũ cốt lõi / Người đóng góp",
  "actions.error.submitFailed": "Gửi không thành công, vui lòng thử lại.",
  "actions.error.verificationFailed": "Xác minh thất bại. Vui lòng thử lại.",
  "addCourse.additionalInfo": "Thông tin bổ sung",
  "addCourse.attendancePolicy": "chính sách tham dự làm việc",
  "addCourse.attendancePolicyPlaceholder": "Vui lòng nhập chính sách hiện diện (tùy chọn)",
  "addCourse.basicInfo": "thông tin cơ bản / basic information",
  "addCourse.batchAddTeachers": "Thêm hàng loạt",
  "addCourse.batchAddTeachersCancel": "Hủy bỏ nó đi",
  "addCourse.batchAddTeachersConfirm": "xác nhận / xác nhận / xác nhận",
  "addCourse.batchAddTeachersDeselectAll": "Hủy chọn tất cả",
  "addCourse.batchAddTeachersPlaceholder": "Vui lòng nhập tên của giáo viên, hỗ trợ nhiều dấu ngăn cách (dấu phẩy, dấu chấm phẩy, dấu chấm phẩy, vv)",
  "addCourse.batchAddTeachersPreview": "Xem trước (Preview)",
  "addCourse.batchAddTeachersSelectAll": "Toàn bộ lựa chọn",
  "addCourse.batchAddTeachersSelectSeparators": "Chọn một dấu ngăn cách",
  "addCourse.batchAddTeachersSelectSeparatorsDesc": "Đã phát hiện nhiều dấu ngăn cách, vui lòng chọn dấu ngăn cách bạn muốn sử dụng:",
  "addCourse.batchAddTeachersTitle": "Thêm giáo viên hàng loạt",
  "addCourse.cancel": "Hủy bỏ nó đi",
  "addCourse.capacity": "công suất (capacity)",
  "addCourse.capacityPlaceholder": "Vui lòng nhập dung lượng khóa học (tùy chọn)",
  "addCourse.classRoom": "Địa điểm của lớp học",
  "addCourse.classRoomPlaceholder": "Vui lòng nhập địa điểm của lớp học (tùy chọn)",
  "addCourse.classTime": "Thời gian học",
  "addCourse.classTimePlaceholder": "Vui lòng nhập giờ học (tùy chọn)",
  "addCourse.clearForm": "Làm trống biểu mẫu",
  "addCourse.code": "Mã khóa học (Mode Course)",
  "addCourse.codePlaceholder": "Vui lòng nhập mã khóa học",
  "addCourse.confirmClear": "Xác nhận trống không",
  "addCourse.confirmClearMessage": "Bạn có chắc chắn muốn làm trống tất cả nội dung biểu mẫu không? Hành động này không thể đảo ngược được.",
  "addCourse.confirmClearTitle": "Xác nhận làm trống biểu mẫu",
  "addCourse.courseContent": "nội dung của khóa học",
  "addCourse.courseContentPlaceholder": "Vui lòng nhập nội dung khóa học (tùy chọn)",
  "addCourse.courseType": "Loại khóa học",
  "addCourse.courseType.elective": "Các môn tự chọn công cộng",
  "addCourse.courseType.major": "lớp học chuyên môn / lớp học chuyên môn",
  "addCourse.courseType.physical": "Lớp học thể thao",
  "addCourse.courseType.required": "Các khóa học bắt buộc công cộng",
  "addCourse.courseTypePlaceholder": "Vui lòng chọn loại khóa học",
  "addCourse.credits": "Tín chỉ",
  "addCourse.creditsPlaceholder": "Vui lòng nhập tín chỉ (0-10)",
  "addCourse.department": "mở lớp học, khoa học, khoa học",
  "addCourse.departmentHelp": "Vui lòng chọn trường từ danh sách, hoặc nhập tên trường để tìm kiếm",
  "addCourse.departmentPlaceholder": "Vui lòng nhập vào Khoa học",
  "addCourse.description": "Mô tả khóa học",
  "addCourse.descriptionPlaceholder": "Vui lòng nhập mô tả khóa học (tùy chọn)",
  "addCourse.electiveField": "Các lĩnh vực tự chọn",
  "addCourse.electiveFieldPlaceholder": "Vui lòng nhập một lĩnh vực tự chọn (tùy chọn)",
  "addCourse.examMethod": "phương thức kiểm tra / phương thức kiểm tra",
  "addCourse.examMethodPlaceholder": "Vui lòng nhập phương thức thi (tùy chọn)",
  "addCourse.gradingMethod": "phương thức đánh giá / phương thức đánh giá",
  "addCourse.gradingMethodPlaceholder": "Vui lòng nhập phương thức đánh giá (tùy chọn)",
  "addCourse.name": "Tên của khóa học",
  "addCourse.namePlaceholder": "Vui lòng nhập tên khóa học",
  "addCourse.prerequisites": "Yêu cầu sửa trước",
  "addCourse.prerequisitesPlaceholder": "Vui lòng nhập yêu cầu trước (tùy chọn)",
  "addCourse.previewEmpty": "Không có nội dung xem trước (Chiều dài: {{length}})",
  "addCourse.professor": "giáo viên giảng dạy / giáo viên giảng dạy",
  "addCourse.professorPlaceholder": "Vui lòng nhập giáo viên giảng dạy (tùy chọn)",
  "addCourse.selectTeacher": "Lựa chọn giáo viên",
  "addCourse.semester": "Học kỳ",
  "addCourse.semesterPlaceholder": "Vui lòng nhập học kỳ (tùy chọn)",
  "addCourse.submitCourse": "Gửi thông tin khóa học",
  "addCourse.submitFailed": "Gửi không thành công, vui lòng thử lại",
  "addCourse.submitSuccess": "Thông tin khóa học đã được gửi thành công! Thông tin sẽ được hiển thị sau khi xem xét.",
  "addCourse.subtitle": "Thêm thông tin khóa học mới vào hệ thống",
  "addCourse.title": "Thêm lớp học",
  "addCourse.validation.capacityInvalid": "Dung lượng phải là số nguyên không âm",
  "addCourse.validation.codeRequired": "Vui lòng nhập mã khóa học",
  "addCourse.validation.codeTooLong": "Mã khóa học không được quá 50 ký tự",
  "addCourse.validation.courseExists": "Khóa học \"{name}\" đã tồn tại",
  "addCourse.validation.creditsInvalid": "Tín chỉ phải là số từ 0-10",
  "addCourse.validation.departmentInvalid": "Vui lòng chọn một trường hợp lệ từ danh sách",
  "addCourse.validation.departmentRequired": "Vui lòng nhập vào Khoa học",
  "addCourse.validation.departmentTooLong": "Trường học không được vượt quá 255 ký tự",
  "addCourse.validation.nameRequired": "Vui lòng nhập tên khóa học",
  "addCourse.validation.nameTooLong": "Tên khóa học không được quá 255 ký tự",
  "addCourse.validation.teacherDuplicates": "Tìm thấy các giáo viên trùng lặp: {duplicates}",
  "addCourse.validation.teacherEmpty": "Vui lòng điền vào tất cả tên của giáo viên, không thể có hộp trống",
  "addCourse.validation.turnstileFailed": "Xác minh người máy không thành công, vui lòng thử lại",
  "addCourse.validation.turnstileRequired": "Vui lòng hoàn thành xác minh người máy",
  "addReview.academicContext": "Bối cảnh học thuật",
  "addReview.addCourse": "Thêm khóa học",
  "addReview.addTeacher": "Thêm giảng viên",
  "addReview.batchAddTeachers": "Thêm hàng loạt",
  "addReview.batchAddTeachersCancel": "Hủy",
  "addReview.batchAddTeachersConfirm": "Xác nhận thêm",
  "addReview.batchAddTeachersDeselectAll": "Hủy chọn tất cả",
  "addReview.batchAddTeachersPlaceholder": "Nhập tên giảng viên (hỗ trợ dấu phẩy, dấu chấm phẩy, xuống dòng...)",
  "addReview.batchAddTeachersPreview": "Xem trước kết quả",
  "addReview.batchAddTeachersSelectAll": "Chọn tất cả",
  "addReview.batchAddTeachersSelectSeparators": "Chọn dấu phân cách",
  "addReview.batchAddTeachersSelectSeparatorsDesc": "Đã phát hiện nhiều dấu phân cách, vui lòng chọn:",
  "addReview.batchAddTeachersTitle": "Thêm giảng viên hàng loạt",
  "addReview.below60": "Dưới 60 điểm",
  "addReview.cancel": "Hủy",
  "addReview.clearForm": "Xóa biểu mẫu",
  "addReview.confirmClear": "Xác nhận xóa",
  "addReview.confirmClearMessage": "Bạn có chắc chắn muốn xóa toàn bộ nội dung biểu mẫu?",
  "addReview.confirmClearTitle": "Xác nhận xóa biểu mẫu",
  "addReview.content": "Nội dung đánh giá",
  "addReview.contentPlaceholder": "Nhập nội dung đánh giá khóa học, hỗ trợ Markdown",
  "addReview.course": "Khóa học",
  "addReview.courseGrade": "Thành tích",
  "addReview.courseName": "Tên khóa học",
  "addReview.courseScore": "Điểm số (0-100)",
  "addReview.courseSelection": "Thông tin khóa học",
  "addReview.edit": "Chỉnh sửa",
  "addReview.estimatedGPA": "GPA ước tính",
  "addReview.extraInfo": "Thông tin bổ sung (tùy chọn)",
  "addReview.gpa": "điểm thành tích / điểm thành tích",
  "addReview.gpaFormat": "{gpa}({range} phút)",
  "addReview.gpaInfo": "Lưu thực tế là điểm trung bình và chỉ được khuyến khích sử dụng khi bạn không nhớ điểm cụ thể.",
  "addReview.gpaType": "Điểm thành tích (0-4)",
  "addReview.grade": "thành tích của khóa học",
  "addReview.gradePlaceholder": "Vui lòng nhập điểm số từ 0-100 với số thập phân",
  "addReview.gradeType": "Loại thành tích",
  "addReview.loadingMessage": "Đang lấy thông tin khóa học, xin vui lòng chờ...",
  "addReview.markdownSupport": "Hỗ trợ Markdown",
  "addReview.preview": "Xem trước (Preview)",
  "addReview.rating": "Đánh giá đa chiều",
  "addReview.reviewContent": "Nội dung đánh giá",
  "addReview.reviewTitle": "Tiêu đề đánh giá",
  "addReview.reviewerName": "Tên người đánh giá (Tùy chọn)",
  "addReview.reviewerNamePlaceholder": "Ẩn danh hoặc biệt danh của bạn",
  "addReview.scoreType": "Điểm số (0-100)",
  "addReview.securityVerification": "Xác minh an toàn",
  "addReview.selectCourse": "thông tin cơ bản / basic information",
  "addReview.submitFailed": "Gửi không thành công, vui lòng thử lại",
  "addReview.submitReview": "Gửi bản đánh giá",
  "addReview.submitSuccess": "Đánh giá đã nộp thành công!Đánh giá sẽ được hiển thị sau khi xem xét.",
  "addReview.subtitle": "Chia sẻ kinh nghiệm học tập của bạn và giúp các bạn học khác đưa ra lựa chọn tốt hơn",
  "addReview.teacher": "giáo viên / giáo viên / giáo viên",
  "addReview.teacherName": "Nhập tên của giáo viên…",
  "addReview.title": "Thêm đánh giá khóa học",
  "addReview.titlePlaceholder": "Vui lòng nhập tiêu đề đánh giá (tùy chọn, để trống sẽ được tự động tạo)…",
  "addReview.validation.contentRequired": "Vui lòng nhập nội dung đánh giá",
  "addReview.validation.contentTooShort": "Nội dung đánh giá cần ít nhất 10 ký tự",
  "addReview.validation.gradeInvalid": "Điểm cần phải là số từ 0-100",
  "addReview.validation.gradeRequired": "Vui lòng nhập điểm số của khóa học",
  "addReview.validation.selectCourse": "Vui lòng chọn khóa học",
  "addReview.validation.teacherDuplicates": "Có trùng lặp tên giáo viên: {duplicates}",
  "addReview.validation.teacherEmpty": "Tên giáo viên không thể trống",
  "addReview.validation.titleTooLong": "Tiêu đề không được nhiều hơn 255 ký tự",
  "addReview.validation.turnstileFailed": "Xác minh người máy không thành công, vui lòng thử lại",
  "addReview.validation.turnstileRequired": "Vui lòng hoàn thành xác minh người máy",
  "addReview.verificationDescription": "Vui lòng hoàn thành các xác minh sau đây để đảm bảo an toàn đánh giá:",
  "addReview.verificationRequired": "Vui lòng hoàn thành xác minh",
  "addTeacher.basicInfo": "thông tin cơ bản / basic information",
  "addTeacher.batchAddCourses": "Thêm hàng loạt",
  "addTeacher.batchAddCoursesCancel": "Hủy bỏ nó đi",
  "addTeacher.batchAddCoursesConfirm": "xác nhận / xác nhận / xác nhận",
  "addTeacher.batchAddCoursesDeselectAll": "Hủy chọn tất cả",
  "addTeacher.batchAddCoursesPlaceholder": "Vui lòng nhập tên khóa học, một trong mỗi dòng hoặc chia cách bằng dấu tách",
  "addTeacher.batchAddCoursesPreview": "Xem trước kết quả",
  "addTeacher.batchAddCoursesSelectAll": "Toàn bộ lựa chọn",
  "addTeacher.batchAddCoursesSelectSeparators": "Chọn một dấu ngăn cách",
  "addTeacher.batchAddCoursesSelectSeparatorsDesc": "Đã phát hiện nhiều dấu ngăn cách, vui lòng chọn dấu ngăn cách bạn muốn sử dụng:",
  "addTeacher.batchAddCoursesTitle": "Thêm lớp học theo số lượng lớn",
  "addTeacher.cancel": "Hủy bỏ nó đi",
  "addTeacher.clearForm": "Làm trống biểu mẫu",
  "addTeacher.confirmClear": "Xác nhận trống không",
  "addTeacher.confirmClearMessage": "Bạn có chắc chắn muốn làm trống tất cả nội dung biểu mẫu không? Hành động này không thể đảo ngược được.",
  "addTeacher.confirmClearTitle": "Xác nhận làm trống biểu mẫu",
  "addTeacher.courseName": "Tên của khóa học",
  "addTeacher.courses": "các khóa học giảng dạy",
  "addTeacher.name": "Tên của giáo viên",
  "addTeacher.namePlaceholder": "Vui lòng nhập tên của giáo viên",
  "addTeacher.selectCourses": "Chọn một khóa học",
  "addTeacher.submitFailed": "Gửi không thành công, vui lòng thử lại",
  "addTeacher.submitSuccess": "Thông tin giáo viên nộp thành công! Thông tin sẽ được hiển thị sau khi xem xét.",
  "addTeacher.submitTeacher": "Gửi thông tin của giáo viên",
  "addTeacher.subtitle": "Thêm thông tin giáo viên mới vào hệ thống",
  "addTeacher.title": "Thêm giáo viên",
  "addTeacher.validation.courseDuplicates": "Khóa học trùng lặp được tìm thấy: {duplicates}",
  "addTeacher.validation.courseEmpty": "Vui lòng điền vào tất cả các tên khóa học, không thể có hộp trống",
  "addTeacher.validation.nameRequired": "Vui lòng nhập tên của giáo viên",
  "addTeacher.validation.nameTooLong": "Tên của giáo viên không được quá 255 ký tự",
  "addTeacher.validation.teacherExists": "Giáo viên \"{name}\" đã tồn tại",
  "addTeacher.validation.turnstileFailed": "Xác minh người máy không thành công, vui lòng thử lại",
  "addTeacher.validation.turnstileRequired": "Vui lòng hoàn thành xác minh người máy",
  "admin.accessAndEndpoint": "Truy cập & Điểm cuối",
  "admin.action": "Hành động",
  "admin.actor": "Người thực hiện",
  "admin.adminConsole": "Bảng điều khiển quản trị",
  "admin.apiBase": "API Base",
  "admin.approve": "Phê duyệt",
  "admin.auditLogs": "Nhật ký kiểm tra",
  "admin.authStatus": "Trạng thái xác thực",
  "admin.backoffice.overview": "管理后台概览",
  "admin.confirmLogout": "Bạn có chắc chắn muốn đăng xuất không?",
  "admin.courseMgmt": "Quản lý khóa học",
  "admin.courseName": "Tên khóa học",
  "admin.createCourse": "Tạo khóa học",
  "admin.createUser": "Tạo người dùng",
  "admin.dashboard": "Tổng quan",
  "admin.defaultPageSize": "Kích thước trang mặc định",
  "admin.department": "Khoa/Viện",
  "admin.id": "ID",
  "admin.loadFailed": "Tải thất bại",
  "admin.loggedOut": "Đã đăng xuất",
  "admin.loginButton": "Đăng nhập quản trị",
  "admin.logout": "Đăng xuất",
  "admin.logoutSuccess": "Đăng xuất thành công",
  "admin.name": "Tên",
  "admin.navigation": "Điều hướng",
  "admin.next": "Tiếp theo",
  "admin.page": "Trang",
  "admin.password": "Mật khẩu",
  "admin.pendingReviews": "Đánh giá đang chờ",
  "admin.prev": "Trước",
  "admin.reviewModeration": "Kiểm duyệt đánh giá",
  "admin.reviewModerationEnabled": "Đã bật kiểm duyệt đánh giá",
  "admin.roles.admin": "Quản trị viên",
  "admin.roles.superadmin": "Siêu quản trị viên",
  "admin.roles.user": "Người dùng",
  "admin.saveSettings": "Lưu cài đặt",
  "admin.signedIn": "Đã đăng nhập",
  "admin.signedOut": "Đã đăng xuất",
  "admin.siteDescription": "WHU.sb 管理控制台",
  "admin.siteTitle": "Tiêu đề trang web",
  "admin.siteTitleTemplate": "%s | 管理员",
  "admin.stats": "Thống kê dữ liệu",
  "admin.status": "Trạng thái",
  "admin.systemSettings": "Cài đặt hệ thống",
  "admin.teacherName": "Tên giảng viên",
  "admin.timestamp": "Thời gian",
  "admin.uid": "UID",
  "admin.updateStatus": "Cập nhật trạng thái",
  "admin.userMgmt": "Quản lý người dùng",
  "admin.userUid": "User UID",
  "admin.username": "Tên đăng nhập",
  "app.about.hero.desc": "Đại học Vũ Hán · Các khóa học và nền tảng điều hướng khuôn viên trường",
  "app.about.hero.name": "WHU.sb",
  "app.about.markdown": "# Giới thiệu về chúng tôi\n\nChào mừng bạn đến với **WhuSB - Nền tảng đánh giá khóa học của Đại học Vũ Hán**!\n\nChúng tôi cam kết cung cấp một nền tảng trao đổi đánh giá khóa học cởi mở, minh bạch và công bằng cho sinh viên của Đại học Vũ khí.\n\nỞ đây, bạn có thể:\n- Xem chi tiết về các loại khóa học\n- Đọc đánh giá thực sự của các bạn học\n- Chia sẻ kinh nghiệm học tập của bạn\n- Cung cấp cơ sở tham khảo cho việc lựa chọn các khóa học\n\nHãy cùng nhau xây dựng một môi trường học tập tốt hơn!",
  "app.about.team.title": "Đội ngũ cốt lõi / Người đóng góp",
  "app.common.privacy": "Chính sách bảo mật",
  "app.common.terms": "Điều khoản dịch vụ",
  "app.config.friendlyLinks.calendar.description": "Import WHU Academic Calendar",
  "app.config.friendlyLinks.calendar.name": "Academic Calendar",
  "app.config.friendlyLinks.ham.description": "Ham App",
  "app.config.friendlyLinks.ham.name": "Ham",
  "app.config.navigation.category.management.title": "Management Services",
  "app.config.navigation.category.public.title": "Public Services",
  "app.config.navigation.category.teachingResearch.title": "Teaching & Research",
  "app.config.navigation.links.academicLectures.name": "Academic Lectures",
  "app.config.navigation.links.affairsHall.name": "Affairs Service Hall",
  "app.config.navigation.links.ai4s.name": "Science Navigation (AI4S)",
  "app.config.navigation.links.aiIntelligentAgent.name": "AI Intelligent Agent",
  "app.config.navigation.links.basicCourseAnalysis.name": "Basic Course Grade Analysis",
  "app.config.navigation.links.campusRepair.name": "Campus Repair",
  "app.config.navigation.links.diningIndex.name": "Dining Index",
  "app.config.navigation.links.dormElectricity.name": "Dormitory Electricity",
  "app.config.navigation.links.dormMgmt.name": "Student Dormitory Management",
  "app.config.navigation.links.employmentService.name": "Employment Service",
  "app.config.navigation.links.equipmentSharing.name": "Large Equipment Sharing",
  "app.config.navigation.links.feedback.name": "Feedback",
  "app.config.navigation.links.freeClassroom.name": "Available Classrooms",
  "app.config.navigation.links.gradAdmissions.name": "Graduate Admissions",
  "app.config.navigation.links.gradeQueryUndergrad.name": "Grade Query (Undergraduate)",
  "app.config.navigation.links.graduateServices.name": "Graduate Student Services",
  "app.config.navigation.links.graduationDeparture.name": "Graduation and Departure",
  "app.config.navigation.links.institutionalRepo.name": "Institutional Repository",
  "app.config.navigation.links.libSeatReservation.name": "Library Seat Reservation",
  "app.config.navigation.links.lostFound.name": "Lost and Found",
  "app.config.navigation.links.luojiaEcard.name": "Luojia eCard",
  "app.config.navigation.links.luojiaExpress.name": "Luojia Express",
  "app.config.navigation.links.luojiaOnline.name": "Luojia Online (MOOC)",
  "app.config.navigation.links.medicalHealth.name": "Medical Health",
  "app.config.navigation.links.meicallMovie.name": "Meicall Movie",
  "app.config.navigation.links.mobileLibrary.name": "Mobile Library",
  "app.config.navigation.links.myData.name": "My Data",
  "app.config.navigation.links.networkSelfService.name": "Personal Network Self-Service",
  "app.config.navigation.links.officialWeChat.name": "WHU Official WeChat",
  "app.config.navigation.links.psychologicalService.name": "Student Psychological Service",
  "app.config.navigation.links.secondClassroom.name": "Second Classroom",
  "app.config.navigation.links.studentEvalUndergrad.name": "Student Evaluation (Undergraduate)",
  "app.config.navigation.links.telephoneYellowPages.name": "Telephone Yellow Pages",
  "app.config.navigation.links.thesisLib.name": "Thesis (Library)",
  "app.config.navigation.links.tuitionPayment.name": "Tuition Fee Payment",
  "app.config.navigation.links.undergradAcademic.name": "Undergraduate Academic Affairs",
  "app.config.navigation.links.undergradSchedule.name": "Undergraduate Schedule",
  "app.config.navigation.links.whuJournal.name": "WHU Journal",
  "app.config.navigation.links.youthInnovation.name": "Youth Innovation Luojia X",
  "app.config.utilities.category.campusLife.subtitle": "Common life services",
  "app.config.utilities.category.campusLife.title": "Campus Life",
  "app.config.utilities.category.studyAcademic.subtitle": "Common study and academic tools",
  "app.config.utilities.category.studyAcademic.title": "Study & Academic",
  "app.config.utilities.links.arxiv.description": "Preprint repository",
  "app.config.utilities.links.arxiv.name": "ArXiv",
  "app.config.utilities.links.calendar.description": "WHU Academic Calendar",
  "app.config.utilities.links.calendar.name": "Academic Calendar",
  "app.config.utilities.links.googleScholar.description": "Scholarly search",
  "app.config.utilities.links.googleScholar.name": "Google Scholar",
  "app.config.utilities.links.scheduleToCalendar.description": "Convert class schedule to calendar",
  "app.config.utilities.links.scheduleToCalendar.name": "Class Schedule to Calendar",
  "app.navigation.footer.categoriesLabel": "cái phân loại / cái phân loại",
  "app.navigation.footer.linksLabel": "một liên kết",
  "app.navigation.subtitle": "Truy cập nhanh các trang web phổ biến của trường",
  "app.navigation.title": "Điều hướng trong khuôn viên trường",
  "app.navigation.utilities": "Tiện ích",
  "app.privacy.sections.cache.body": "Chúng tôi sử dụng LocalStorage để lưu các tùy chọn chủ đề, lựa chọn ngôn ngữ và các bản nháp biểu mẫu tạm thời của bạn. Tất cả dữ liệu này được lưu trữ cục bộ trên thiết bị của bạn và sẽ không được tải lên máy chủ của chúng tôi.",
  "app.privacy.sections.cache.title": "Cookie và Bộ nhớ đệm",
  "app.privacy.sections.collection.body": "WHU.sb chỉ thu thập dữ liệu liên quan đến khóa học như thông tin đánh giá, học kỳ và năm học mà bạn tự nguyện cung cấp. Hệ thống của chúng tôi không chủ động thu thập tên thật, mã số sinh viên hoặc bất kỳ thông tin nhạy cảm trực tiếp nào của bạn.",
  "app.privacy.sections.collection.title": "Thu thập dữ liệu",
  "app.privacy.sections.contact.body": "Nếu bạn có bất kỳ câu hỏi nào về các vấn đề quyền riêng tư hoặc nếu bạn tin rằng một đánh giá vi phạm quyền lợi của bạn, vui lòng liên hệ với đội ngũ hỗ trợ của chúng tôi hoặc gửi khiếu nại qua GitHub.",
  "app.privacy.sections.contact.title": "Liên hệ với chúng tôi",
  "app.privacy.subtitle": "Chính sách bảo mật",
  "app.privacy.title": "Chính sách bảo mật",
  "app.terms.sections.conduct.body": "WHU.sb nhằm mục đích cung cấp một môi trường trao đổi học thuật hài hòa và chân thực. Nghiêm cấm đăng bất kỳ nội dung sai sự thật, lăng mạ, quảng cáo hoặc gây kích động không liên quan đến khóa học. Chúng tôi có quyền xóa các nội dung không phù hợp.",
  "app.terms.sections.conduct.title": "Hướng dẫn sử dụng",
  "app.terms.sections.copyright.body": "Mã nguồn nền tảng WHU.sb được nguồn mở theo giấy phép MIT. Bản quyền của nội dung văn bản do người dùng đăng thuộc về tác giả, nhưng nền tảng được ủy quyền sử dụng miễn phí vĩnh viễn trên toàn cầu.",
  "app.terms.sections.copyright.title": "Bản quyền và Thỏa thuận",
  "app.terms.sections.disclaimer.body": "Tất cả các đánh giá trên nền tảng này là quan điểm cá nhân của người dùng và không đại diện cho lập trường của Đại học Vũ Hán chính thức hoặc đội ngũ dự án. Thông tin đánh giá chỉ mang tính chất tham khảo, quyết định và hậu quả của việc chọn khóa học do cá nhân tự chịu trách nhiệm.",
  "app.terms.sections.disclaimer.title": "Tuyên bố miễn trừ trách nhiệm",
  "app.terms.subtitle": "Điều khoản dịch vụ",
  "app.terms.title": "Điều khoản dịch vụ",
  "auth.back": "Quay lại trang trước",
  "auth.confirmPassword": "Xác nhận mật khẩu",
  "auth.email": "Hộp thư / Hộp thư",
  "auth.loggingIn": "Đang đăng nhập…",
  "auth.login": "Đăng nhập vào đây",
  "auth.loginTab": "Đăng nhập vào đây",
  "auth.logout": "Đăng xuất",
  "auth.password": "Mật khẩu",
  "auth.register": "Đăng ký",
  "auth.registerTab": "Đăng ký",
  "auth.registering": "Đang đăng ký…",
  "cacheTest.cacheStatus": "trạng thái bộ nhớ đệm",
  "cacheTest.cacheStatusCheckComplete": "📊 Kiểm tra trạng thái bộ nhớ đệm đã hoàn thành",
  "cacheTest.cacheTest": "Trang kiểm tra bộ nhớ đệm",
  "cacheTest.cacheTestDescription": "Để kiểm tra và xác minh hiệu quả sửa chữa bộ nhớ đệm",
  "cacheTest.clearAllCache": "Xóa tất cả bộ nhớ đệm",
  "cacheTest.clearCourseCache": "Xóa bộ nhớ đệm khóa học",
  "cacheTest.courseCacheClearFailed": "Làm sạch bộ nhớ đệm khóa học không thành công",
  "cacheTest.courseCacheClearSuccess": "Dọn dẹp bộ nhớ đệm khóa học thành công",
  "cacheTest.courseCacheCleared": "✅ Đã xóa bộ nhớ đệm khóa học",
  "cacheTest.courseDetailCacheTest": "Chi tiết khóa học Kiểm tra bộ nhớ đệm",
  "cacheTest.getCacheStatus": "Lấy trạng thái bộ nhớ đệm",
  "cacheTest.getCacheStatusFailedTitle": "Lỗi trong việc lấy trạng thái bộ nhớ đệm",
  "cacheTest.goToRandomPage": "Đi đến trang tốt đẹp",
  "cacheTest.quickCourseSwitchDescription": "Nhấp vào các liên kết dưới đây để nhanh chóng chuyển đổi các khóa học và xem có vấn đề bộ nhớ đệm không:",
  "common.admin": "Quản trị",
  "common.all": "Tất cả",
  "common.anonymous": "Ẩn danh",
  "common.appName": "WHU.sb",
  "common.apply": "Áp dụng",
  "common.author": "Tác giả",
  "common.back": "Quay lại",
  "common.cacheManagement": "Quản lý bộ nhớ đệm",
  "common.cached": "Đã lưu bộ nhớ đệm",
  "common.cancel": "Hủy",
  "common.clear": "Xóa",
  "common.cleared": "Đã xóa",
  "common.close": "Đóng",
  "common.confirm": "Xác nhận",
  "common.confirmClear": "Xác nhận xóa",
  "common.copied": "Đã sao chép",
  "common.copy": "Sao chép",
  "common.copyFailed": "Sao chép thất bại",
  "common.done": "Hoàn tất",
  "common.error.message": "Đã xảy ra lỗi không mong muốn khi tải nội dung. Vui lòng kiểm tra kết nối của bạn và thử lại.",
  "common.error.pageNotFound": "Lạc đường? Trang này đã biến mất giữa những đồi Luojia.",
  "common.error.searchHint": "Thử tìm kiếm khóa học hoặc giảng viên bạn đang tìm:",
  "common.error.title": "Đã xảy ra lỗi",
  "common.formatError": "Lỗi định dạng",
  "common.items": "mục",
  "common.language": "ngôn ngữ / ngôn ngữ",
  "common.lastUpdated": "Cập nhật lần cuối: {date}",
  "common.loading": "Đang tải…",
  "common.menu": "Menu của bạn",
  "common.more": "更多",
  "common.name": "Tên",
  "common.next": "Tiếp theo",
  "common.noData": "Không có dữ liệu",
  "common.noRating": "Chưa có đánh giá",
  "common.notCached": "Chưa lưu bộ nhớ đệm",
  "common.numericPlaceholder": "ví dụ: 123456",
  "common.page": "Trang {page}",
  "common.pagination": "Phân trang",
  "common.people": "người",
  "common.pinyin": "Pinyin",
  "common.previous": "Trước",
  "common.refresh": "Làm mới",
  "common.reset": "Đặt lại",
  "common.retry": "Hãy thử lại",
  "common.share": "Chia sẻ với nhau",
  "common.startSearching": "Bắt đầu tìm kiếm khóa học",
  "common.startSearchingHint": "Sử dụng công cụ tìm kiếm ở trên để tìm các khóa học mà bạn quan tâm",
  "common.submitTime": "Thời gian nộp đơn",
  "common.success": "thành công",
  "common.theme": "chủ đề / chủ đề",
  "common.unknown": "không biết",
  "common.unknownTeacher": "giáo viên không biết",
  "common.unknownTime": "Thời gian không biết",
  "common.updateManagement": "Quản lý Cập Nhật",
  "common.user": "người dùng (user)",
  "course.detail.addReview": "Viết đánh giá của tôi",
  "course.detail.basic": "Thông tin cơ bản về khóa học",
  "course.detail.credits": "Tín chỉ học thuật",
  "course.detail.dept": "Đơn vị giảng dạy",
  "course.detail.name": "Tên chính thức",
  "course.detail.noReviews": "Chưa có đánh giá hợp lệ",
  "course.detail.noReviewsNotice": "Hãy là người đầu tiên để lại dấu chân!",
  "course.detail.radar": "Dấu vân tay học thuật",
  "course.detail.reviews": "Đánh giá của sinh viên",
  "course.detail.teacher": "Giảng viên chính",
  "courseDetail.attendancePolicy": "chính sách tham dự làm việc",
  "courseDetail.basedOnReviews": "Dựa trên đánh giá {n}",
  "courseDetail.classRoom": "Địa điểm của lớp học",
  "courseDetail.classTime": "Thời gian học",
  "courseDetail.courseCapacity": "Khả năng của khóa học",
  "courseDetail.courseCode": "Mã khóa học (Mode Course)",
  "courseDetail.courseContent": "nội dung của khóa học",
  "courseDetail.courseIntroduction": "Giới thiệu ngắn gọn về khóa học",
  "courseDetail.creationTime": "Thời gian tạo ra",
  "courseDetail.credits": "Tín chỉ",
  "courseDetail.creditsUnit": "Tín chỉ",
  "courseDetail.department": "mở lớp học, khoa học, khoa học",
  "courseDetail.description": "Trang chi tiết khóa học",
  "courseDetail.difficultRating": "Đánh giá khó khăn",
  "courseDetail.easyRating": "Đơn giản đánh giá",
  "courseDetail.examMethod": "phương thức thẩm định / phương thức thẩm định",
  "courseDetail.gradingMethod": "phương thức đánh giá / phương thức đánh giá",
  "courseDetail.hamDataSupport": "Hỗ trợ dữ liệu bởi Ham",
  "courseDetail.loadFailed": "Nạp lỗi",
  "courseDetail.multiDimensionalRating": "Đánh giá nhiều chiều cho các khóa học",
  "courseDetail.noDescription": "tạm thời không có hồ sơ",
  "courseDetail.prerequisites": "Yêu cầu sửa trước",
  "courseDetail.reviews": "đánh giá / đánh giá / đánh giá",
  "courseDetail.semester": "học kỳ mở lớp học",
  "courseDetail.teachingTeacher": "giáo viên giảng dạy / giáo viên giảng dạy",
  "courseDetail.title": "Chi tiết khóa học",
  "courseDetail.totalComments": "Tổng số bình luận",
  "courseDetail.updateTime": "Thời gian cập nhật",
  "courseDetail.viewAllReviews": "Xem tất cả các đánh giá",
  "courseDetail.writeReview": "viết đánh giá",
  "courseTeacherDetail.averageRating": "Điểm số trung bình",
  "courseTeacherDetail.averageScore": "điểm trung bình / điểm trung bình",
  "courseTeacherDetail.courseIntroduction": "Giới thiệu ngắn gọn về khóa học",
  "courseTeacherDetail.fetchOtherTeachersFailed": "Lấy thông tin của giáo viên khác không thành công",
  "courseTeacherDetail.fetchTeacherFailed": "Lấy thông tin của giáo viên không thành công",
  "courseTeacherDetail.hamCourseScoreDistribution": "Phân phối điểm số khóa học Ham",
  "courseTeacherDetail.hamDataSupport": "Hỗ trợ dữ liệu bởi Ham",
  "courseTeacherDetail.hamNoData": "Ham chưa có dữ liệu đánh giá cho khóa học này",
  "courseTeacherDetail.loadingHamData": "Nạp dữ liệu Ham…",
  "courseTeacherDetail.multiDimensionalRating": "Đánh giá nhiều chiều cho các khóa học",
  "courseTeacherDetail.noDescription": "tạm thời không có hồ sơ",
  "courseTeacherDetail.otherTeachers": "Các giáo viên khác của khóa học này",
  "courseTeacherDetail.reviews": "đánh giá / đánh giá / đánh giá",
  "courseTeacherDetail.reviewsOf": "sự đánh giá của",
  "courseTeacherDetail.score": "Phân điểm",
  "courseTeacherDetail.teachingTeacher": "giáo viên giảng dạy / giáo viên giảng dạy",
  "courseTeacherDetail.title": "Chi tiết của giáo viên khóa học",
  "courseTeacherDetail.totalReviews": "tổng đánh giá / tổng đánh giá",
  "courses.backToCourse": "Trở lại lớp học",
  "courses.courseCode": "Mã khóa học (Mode Course)",
  "courses.courseName": "Tên của khóa học",
  "courses.credits": "Tín chỉ",
  "courses.department": "mở lớp học, khoa học, khoa học",
  "courses.fetchTeachersError": "Lấy thông tin của giáo viên không thành công",
  "courses.loadingTeachers": "Nạp thông tin giáo viên…",
  "courses.review": "bài đánh giá / bài đánh giá",
  "courses.reviews": "bài đánh giá / bài đánh giá",
  "courses.semester": "Học kỳ",
  "courses.teacher": "giáo viên giảng dạy / giáo viên giảng dạy",
  "courses.teachers": "giáo viên giảng dạy / giáo viên giảng dạy",
  "courses.teachersHint": "(Nhấp vào tên giáo viên để vào hồ sơ giảng viên khóa học)",
  "error.403": "Truy cập bị cấm (403)",
  "error.404": "Không tìm thấy trang (404)",
  "error.FORBIDDEN": "Truy cập bị cấm, bạn không có quyền.",
  "error.NETWORK_ERROR": "Yêu cầu mạng thất bại, vui lòng kiểm tra kết nối.",
  "error.NOT_FOUND": "Không tìm thấy tài nguyên yêu cầu.",
  "error.RATE_LIMITED": "Quá nhiều yêu cầu, vui lòng thử lại sau.",
  "error.SERVER_ERROR": "Lỗi máy chủ nội bộ, vui lòng thử lại sau.",
  "error.UNAUTHORIZED": "Chưa xác thực hoặc phiên đã hết hạn, vui lòng đăng nhập lại.",
  "error.UNKNOWN": "Đã xảy ra lỗi không xác định.",
  "error.backHome": "Quay lại trang chủ",
  "error.contentLoadFailed": "Không thể tải nội dung. Vui lòng thử lại sau.",
  "error.oops": "Rất tiếc, đã xảy ra lỗi",
  "error.tryAgain": "Thử lại",
  "error.unexpected": "Ứng dụng gặp lỗi không mong muốn. Vui lòng thử làm mới trang.",
  "error.unknown.title": "Lỗi yêu cầu",
  "error.unkown.message": "Lỗi không xác định.",
  "error.validationError": "Xác thực dữ liệu thất bại, vui lòng kiểm tra định dạng nhập.",
  "examMethods.exam": "kỳ thi / kỳ thi / kỳ thi",
  "examMethods.inspection": "khảo tra / khảo tra / khảo tra",
  "examMethods.other": "những thứ khác",
  "examMethods.project": "Dự án / dự án / dự án",
  "examMethods.thesis": "luận văn / luận văn / luận văn",
  "home.addReview": "Thêm đánh giá",
  "home.luckyButton": "Xem vận may",
  "home.luckyButtonSmallMobile": "Ngẫu nhiên",
  "home.luckySearch": "Cảm thấy may mắn",
  "home.metadata.description": "Tìm kiếm các khóa học tốt nhất và chia sẻ kinh nghiệm học tập của bạn tại Đại học Vũ Hán.",
  "home.metadata.keywords": "Đại học Vũ Hán, Đánh giá khóa học, Đánh giá giảng viên, Môn tự chọn",
  "home.metadata.title": "WHU.sb | Khám phá các khóa học tốt hơn",
  "home.pageHint": "Nhập khóa học, tên giáo viên vào hộp tìm kiếm phía trên, nhấp vào tìm kiếm để tìm đánh giá khóa học",
  "home.searchButtonMobile": "tìm kiếm / tìm kiếm / tìm kiếm",
  "home.searchButtonSmallMobile": "tìm kiếm / tìm kiếm / tìm kiếm",
  "home.searchButtonText": "tìm kiếm / tìm kiếm / tìm kiếm",
  "home.searchPlaceholder": "Tìm kiếm khóa học, giáo viên hoặc từ khóa…",
  "home.searchPlaceholderMobile": "Tìm kiếm các khóa học…",
  "home.searchPlaceholderSmallMobile": "Tìm kiếm... Tìm kiếm",
  "home.subtitle": "Khám phá các khóa học tốt nhất và chia sẻ kinh nghiệm học tập của bạn",
  "home.title": "WHU.sb",
  "home.welcome.0": "Hôm nay bạn muốn tìm kiếm gì?",
  "home.welcome.1": "Khám phá các khóa học thú vị",
  "home.welcome.2": "Xem mọi người nói gì về các giảng viên",
  "home.welcome.3": "Tìm những môn tự chọn thú vị tiềm ẩn",
  "home.welcome.4": "Tìm kiếm những gì bạn quan tâm",
  "home.welcome.5": "Bạn muốn nghe lời khuyên từ các tiền bối?",
  "home.welcome.6": "Xem liệu khóa học này có thực sự xứng đáng để theo học không",
  "loading.failed": "Nạp lỗi",
  "loading.text": "Đang tải…",
  "mobile.userCenter.description": "Quản lý token và định danh ứng dụng cá nhân trên iOS/Android.",
  "navigation.about": "Giới thiệu",
  "navigation.addCourse": "Thêm khóa học",
  "navigation.addReview": "Đánh giá",
  "navigation.addTeacher": "Thêm giảng viên",
  "navigation.adminCenter": "Trung tâm quản trị",
  "navigation.calendar": "Lịch học",
  "navigation.courses": "Khóa học",
  "navigation.home": "Trang chủ",
  "navigation.itemsCount": "{count} mục",
  "navigation.language": "Ngôn ngữ",
  "navigation.login": "Đăng nhập",
  "navigation.more": "Thêm",
  "navigation.myReviews": "Đánh giá của tôi",
  "navigation.privacy": "Chính sách bảo mật",
  "navigation.profile": "Người dùng",
  "navigation.random": "Ngẫu nhiên",
  "navigation.redirectingTo": "Sắp chuyển hướng đến: {name}",
  "navigation.register": "Đăng ký",
  "navigation.reviews": "Đánh giá",
  "navigation.search": "Tìm kiếm",
  "navigation.settings": "Cài đặt",
  "navigation.summary": "{categories} danh mục, {links} liên kết chung",
  "navigation.teachers": "Giảng viên",
  "navigation.terms": "Điều khoản dịch vụ",
  "navigation.theme": "Giao diện",
  "navigation.user": "Người dùng",
  "navigation.userCenter": "Trung tâm người dùng",
  "navigation.utilities": "Tiện ích",
  "notFound.hint": "Thử tìm kiếm khóa học hoặc giảng viên mà bạn đang tìm kiếm:",
  "notFound.lost": "Lối này? Trang này đã biến mất giữa những ngọn đồi Luojia.",
  "pagination.navigation": "Điều hướng theo trang",
  "pagination.next": "Trang tiếp theo",
  "pagination.previous": "Trang trước / Trang trước",
  "pwa.apiCache": "Bộ nhớ đệm API",
  "pwa.appVersion": "Phiên bản của ứng dụng",
  "pwa.cacheAndNav": "Bộ nhớ đệm và điều hướng",
  "pwa.cacheManagement": "Quản lý bộ nhớ đệm cục bộ",
  "pwa.checkUpdate.complete": "Kiểm tra xong rồi",
  "pwa.checkUpdate.failed": "Kiểm tra không thành công",
  "pwa.checkUpdate.latest": "đã là phiên bản mới nhất",
  "pwa.checkUpdate.newVersion": "Tìm thấy phiên bản mới",
  "pwa.checkUpdate.retryLater": "Không thể kiểm tra bản cập nhật, vui lòng thử lại sau",
  "pwa.clearAllCacheSuccess": "Tất cả bộ nhớ đệm đã được xóa",
  "pwa.clearCacheFailed": "Lỗi xóa bộ nhớ cache",
  "pwa.clearDismissedSuccess": "Trạng thái cập nhật sau đã được xóa",
  "pwa.clearFailed": "Dọn dẹp không thành công",
  "pwa.clearIgnoredVersionsSuccess": "Bỏ qua danh sách phiên bản đã được xóa",
  "pwa.clearSuccess": "Dọn sạch thành công",
  "pwa.clearUpdateSuccess": "Lời nhắc cập nhật đã được xóa",
  "pwa.confirmReset": "Bạn có chắc chắn muốn thực hiện cài đặt lại khẩn cấp không? Việc này sẽ đóng trang hiện tại để đặt lại Service Worker.",
  "pwa.connectionStatus": "trạng thái kết nối",
  "pwa.connectionTest": "Kiểm tra kết nối",
  "pwa.connectionTestError": "Lỗi xảy ra trong quá trình thử nghiệm",
  "pwa.connectionTestFailed": "Kết nối Service Worker không thành công",
  "pwa.connectionTestSuccess": "Service Worker kết nối bình thường",
  "pwa.connectionType": "Kiểu kết nối (Connect Type)",
  "pwa.debugInfo": "Thông tin gỡ lỗi",
  "pwa.debugInfoDetail": "Thông tin gỡ lỗi PWA chi tiết đã được xuất vào bảng điều khiển",
  "pwa.items": "mục / mục / mục",
  "pwa.lastUpdate": "Cập nhật cuối cùng",
  "pwa.mobileAppNav": "Di động ứng dụng điều hướng",
  "pwa.mobileAppNavDescription": "Cho phép hệ thống điều hướng theo phong cách ứng dụng di động, bao gồm các thanh điều hướng trên cùng và dưới cùng, phù hợp để sử dụng khi đóng gói thành ứng dụng Android.",
  "pwa.mobileAppNavDisabled": "Vô hiệu hóa điều hướng ứng dụng di động",
  "pwa.mobileAppNavEnabled": "Bật điều hướng ứng dụng di động",
  "pwa.mobileAppNavForceDisabled": "Biến môi trường hiện tại buộc phải vô hiệu hóa điều hướng di động và không thể thay đổi.",
  "pwa.mobileAppNavForceDisabledBadge": "Cưỡng chế cấm sử dụng",
  "pwa.mobileAppNavForceEnabled": "Chế độ xây dựng hiện tại cho ứng dụng, điều hướng di động được bật và không thể thay đổi.",
  "pwa.mobileAppNavForceEnabledBadge": "Bắt buộc kích hoạt",
  "pwa.networkStatus": "trạng thái mạng lưới",
  "pwa.newVersionAvailable": "Phát hiện phiên bản mới có sẵn",
  "pwa.resetDescription": "Hủy đăng ký hoàn toàn Service Worker và xóa dữ liệu ứng dụng. Sử dụng khi ứng dụng không thể cập nhật hoặc hoạt động bất thường.",
  "pwa.resetFailed": "Đặt lại lỗi",
  "pwa.resetSWFailed": "Service Worker không được thiết lập lại",
  "pwa.resetSWSuccess": "Service Worker đã được đặt lại và trang sẽ được tải lại",
  "pwa.resetSuccess": "Đặt lại thành công",
  "pwa.settings.checkUpdate": "Kiểm tra các bản cập nhật",
  "pwa.settings.clearAllCache": "Xóa tất cả bộ nhớ đệm",
  "pwa.settings.clearDismissedState": "Xóa trạng thái cập nhật sau",
  "pwa.settings.clearIgnoredVersions": "Xóa bỏ qua phiên bản",
  "pwa.settings.clearUpdatePrompt": "Dọn dẹp dòng nhắc cập nhật",
  "pwa.settings.debugInfo": "Thông tin gỡ lỗi",
  "pwa.settings.forceRefresh": "Cưỡng chế làm mới",
  "pwa.settings.forceResetSW": "Cưỡng chế đặt lại SW",
  "pwa.settings.showDebugInfo": "Hiển thị thông tin gỡ lỗi",
  "pwa.settings.subtitle": "Quản lý bộ nhớ đệm ứng dụng và cập nhật",
  "pwa.settings.testConnection": "Kiểm tra kết nối",
  "pwa.settings.testWasmSupport": "Kiểm tra hỗ trợ WASM",
  "pwa.settings.title": "Cài đặt",
  "pwa.settings.updateNow": "Cập nhật ngay lập tức",
  "pwa.staticResourceCache": "Bộ nhớ đệm tài nguyên tĩnh",
  "pwa.status.offline": "Ngắt kết nối (offline)",
  "pwa.status.online": "trực tuyến, trực tuyến, trực tuyến",
  "pwa.status.unknown": "không biết",
  "pwa.swVersion": "Phiên bản Service Worker",
  "pwa.systemInfo": "Thông tin hệ thống",
  "pwa.unknown": "không biết",
  "pwa.update.failed": "Cập nhật lỗi",
  "pwa.update.manualRefresh": "Vui lòng làm mới trang bằng tay",
  "pwa.updatePrompt.currentVersion": "Phiên bản hiện tại",
  "pwa.updatePrompt.description": "Các phiên bản mới của ứng dụng có sẵn và chúng tôi khuyên bạn nên cập nhật ngay lập tức để có trải nghiệm tốt nhất.",
  "pwa.updatePrompt.hideDetails": "Ẩn chi tiết",
  "pwa.updatePrompt.ignoreVersion": "Bỏ qua phiên bản này",
  "pwa.updatePrompt.later": "Cập nhật sau",
  "pwa.updatePrompt.newVersion": "Phiên bản mới",
  "pwa.updatePrompt.showDetails": "Hiển thị chi tiết",
  "pwa.updatePrompt.title": "Tìm thấy phiên bản mới",
  "pwa.updatePrompt.unknown": "không biết",
  "pwa.updatePrompt.updateNow": "Cập nhật ngay lập tức",
  "pwa.versionInfo": "Thông tin phiên bản",
  "random.all": "nội dung ngẫu nhiên",
  "random.categories.all": "tất cả mọi thứ",
  "random.categories.courses": "khóa học / khóa học",
  "random.categories.reviews": "đánh giá / đánh giá / đánh giá",
  "random.categories.teachers": "giáo viên / giáo viên / giáo viên",
  "random.courses": "Các khóa học ngẫu nhiên",
  "random.fetchError": "Lấy lỗi",
  "random.fetchErrorDetail": "Không thể lấy nội dung ngẫu nhiên, hãy thử lại sau",
  "random.fetchFailed": "Lấy dữ liệu không thành công, vui lòng thử lại sau",
  "random.noDataMessage": "Không tìm thấy nội dung ngẫu nhiên phù hợp",
  "random.preferChallenging": "và thách thức hơn",
  "random.preferEasy": "dễ dàng hơn",
  "random.reviews": "đánh giá ngẫu nhiên",
  "random.subtitle": "Khám phá các khóa học, giáo viên và đánh giá chất lượng cao",
  "random.title": "tay khí tốt lắm",
  "reviewDetail.relatedCourses": "Các khóa học liên quan",
  "reviewDetail.relatedTeachers": "giáo viên có liên quan",
  "reviewDetail.semester": "Học kỳ",
  "reviews.addReview": "Thêm đánh giá",
  "reviews.anonymousUser": "Người dùng ẩn danh",
  "reviews.assignmentReview": "Bài tập & Công việc",
  "reviews.assignmentReviewPlaceholder": "Mô tả loại, độ khó, tần suất bài tập...",
  "reviews.attendanceReview": "Tình hình điểm danh",
  "reviews.attendanceReviewPlaceholder": "Mô tả yêu cầu điểm danh và tham gia khóa học này...",
  "reviews.beFirstReview": "Hãy là người đầu tiên đánh giá khóa học này!",
  "reviews.boring": "Nhàm chán",
  "reviews.clickToViewFull": "Nhấp để xem đánh giá đầy đủ",
  "reviews.courseInterest": "Độ thú vị",
  "reviews.credits": "Tín chỉ",
  "reviews.criteria.courseInterest": "Độ thú vị",
  "reviews.criteria.difficulty": "Độ khó",
  "reviews.criteria.teachingQuality": "Chất lượng giảng dạy",
  "reviews.criteria.workload": "Khối lượng công việc",
  "reviews.detail": "Chi tiết đánh giá",
  "reviews.detail.title": "Chi tiết đánh giá",
  "reviews.detailedRatings": "Đánh giá chi tiết",
  "reviews.difficulty": "Độ khó của khóa học",
  "reviews.easy": "Đơn giản",
  "reviews.examReview": "Tình huống thi",
  "reviews.examReviewPlaceholder": "Mô tả mức độ khó của bài thi cuối kỳ, loại bài, đề xuất xem lại…",
  "reviews.excellent": "Xuất sắc",
  "reviews.extraInfo": "Thông tin bổ sung",
  "reviews.fair": "Tổng quát",
  "reviews.good": "Tốt",
  "reviews.grade": "Thành tích",
  "reviews.hard": "Khó",
  "reviews.heavy": "Nặng",
  "reviews.interesting": "Thật thú vị",
  "reviews.light": "Thư giãn một chút",
  "reviews.list.courseDescription": "Tất cả các đánh giá cho {courseName}",
  "reviews.list.description": "Xem tất cả các đánh giá khóa học",
  "reviews.list.title": "Danh sách đánh giá",
  "reviews.moderate": "Vừa phải",
  "reviews.noContent": "Đánh giá này không có nội dung văn bản.",
  "reviews.noReviews": "Tạm thời không có đánh giá",
  "reviews.noReviewsMessage": "Chưa có đánh giá nào về giáo viên này",
  "reviews.notRated": "Không được đánh giá",
  "reviews.overallRating": "Đánh giá tổng thể",
  "reviews.poor": "Tương đối kém",
  "reviews.ratingRequired": "Yêu cầu đánh giá",
  "reviews.ratingSelectPrompt": "Vui lòng chọn 1-5 điểm",
  "reviews.review": "Đánh giá",
  "reviews.reviewContent": "Nội dung đánh giá",
  "reviews.tags": "Các nhãn (thẻ)",
  "reviews.teachers": "Giảng viên",
  "reviews.teachingQuality": "Chất lượng giảng dạy",
  "reviews.title": "Đánh giá các khóa học",
  "reviews.totalReviews": "Tổng số đánh giá",
  "reviews.veryBoring": "Rất nhàm chán",
  "reviews.veryEasy": "Rất đơn giản",
  "reviews.veryGood": "Rất tốt",
  "reviews.veryHard": "Rất khó",
  "reviews.veryHeavy": "Rất nặng",
  "reviews.veryInteresting": "Thật là thú vị",
  "reviews.veryLight": "Rất dễ dàng",
  "reviews.veryLittle": "Rất ít",
  "reviews.veryMuch": "Rất nhiều",
  "reviews.veryPoor": "Rất tệ",
  "reviews.viewAllReviews": "Xem tất cả các đánh giá",
  "reviews.workload": "Khối lượng công việc",
  "search.addCondition": "Thêm điều kiện",
  "search.addConditionTip": "Thêm điều kiện: Tạo một điều kiện tìm kiếm đơn lẻ",
  "search.addCourseReview": "Thêm đánh giá khóa học",
  "search.addCourseReviewMobile": "Đánh giá",
  "search.addGroup": "Thêm một nhóm",
  "search.addGroupTip": "Thêm nhóm: Tạo nhóm ngoặc kép",
  "search.advanced": "Nâng cao",
  "search.advancedFilter": "Bộ lọc nâng cao",
  "search.advancedQueryBuilder": "Trình tạo truy vấn nâng cao",
  "search.advancedSearch": "Tìm kiếm nâng cao",
  "search.advancedSearchOptions": "Tùy chọn tìm kiếm nâng cao",
  "search.allConditionsCleared": "Tất cả các điều kiện truy vấn đã bị xóa",
  "search.and": "Và",
  "search.andExample": "A và B",
  "search.andExplanation": "Cả A và B phải thỏa mãn",
  "search.applyFilters": "Áp dụng bộ lọc",
  "search.applyQuery": "Áp dụng truy vấn",
  "search.attendanceAndHomework": "Tham dự và làm việc",
  "search.basicCourseInfo": "Thông tin khóa học cơ bản",
  "search.builder": "Trình tạo",
  "search.builder.addCondition": "Thêm điều kiện",
  "search.builder.apply": "Tạo truy vấn",
  "search.builder.fields.capacity": "Sức chứa",
  "search.builder.fields.code": "Mã khóa học",
  "search.builder.fields.course_name": "Tên khóa học",
  "search.builder.fields.credits": "Tín chỉ",
  "search.builder.fields.department": "Khoa/Viện",
  "search.builder.fields.professor": "Giảng viên",
  "search.builder.operators.contains": "Chứa",
  "search.builder.operators.eq": "Bằng",
  "search.builder.operators.gt": "Lớn hơn",
  "search.builder.operators.lt": "Nhỏ hơn",
  "search.builder.operators.not_contains": "Không chứa",
  "search.builder.reset": "Xóa điều kiện",
  "search.capacity": "Sức chứa",
  "search.classRoom": "Địa điểm lớp học",
  "search.classTime": "Thời gian học",
  "search.clearConditions": "Xóa điều kiện",
  "search.clickAddConditionOrGroup": "Nhấp vào \"Thêm điều kiện\" hoặc \"Thêm nhóm\" để bắt đầu xây dựng truy vấn",
  "search.confirmClearQuery": "Xác nhận việc xóa truy vấn",
  "search.confirmClearQueryMessage": "Bạn có chắc chắn muốn xóa tất cả các điều kiện truy vấn không? Hành động này không thể đảo ngược được.",
  "search.contains": "Bao gồm",
  "search.copyFailed": "Sao chép lỗi",
  "search.copyQuery": "Sao chép cú pháp truy vấn",
  "search.courseAttribute": "Thuộc tính khóa học",
  "search.courseCategoryAndAttributes": "Phân loại và thuộc tính khóa học",
  "search.courseContent": "Nội dung khóa học",
  "search.courseContentAndEvaluation": "Nội dung khóa học và đánh giá",
  "search.courseDetails": "Chi tiết khóa học",
  "search.courseGrade": "Thành tích khóa học",
  "search.courseInterest": "Mức độ hứng thú khóa học",
  "search.courseName": "Tên khóa học",
  "search.courseRatingRange": "Phạm vi đánh giá khóa học",
  "search.courseSchedule": "Thông tin chương trình giảng dạy",
  "search.courseType": "Loại khóa học",
  "search.credits": "Tín chỉ",
  "search.currentRange": "Hiện tại {start} - {end}",
  "search.deleteCondition": "Xóa điều kiện",
  "search.deleteGroup": "Xóa nhóm",
  "search.describeAttendancePolicy": "Mô tả các yêu cầu tham dự và công việc…",
  "search.describeCourseContent": "Mô tả nội dung khóa học, phương pháp giảng dạy…",
  "search.describeGradingMethod": "Mô tả cách đánh giá…",
  "search.describePrerequisites": "Mô tả các yêu cầu của khóa học trước…",
  "search.description": "Mô tả khóa học",
  "search.difficulty": "Độ khó",
  "search.dragTip": "Chức năng kéo: Nhấp vào và kéo biểu tượng thanh ở bên trái để thay đổi thứ tự điều kiện hoặc di chuyển vào nhóm",
  "search.electiveField": "Các môn học tự chọn công cộng",
  "search.endsWith": "Kết thúc bằng",
  "search.enterCapacity": "Nhập sức chứa",
  "search.enterClassRoom": "Nhập địa điểm học",
  "search.enterClassTime": "Nhập giờ học",
  "search.enterCourseCode": "Nhập mã khóa học",
  "search.enterCourseGrade": "Nhập điểm số khóa học",
  "search.enterCourseInterest": "Nhập mức độ quan tâm khóa học",
  "search.enterCourseName": "Nhập tên khóa học",
  "search.enterDifficulty": "Nhập độ khó",
  "search.enterRating": "Nhập điểm số",
  "search.enterReviewerName": "Nhập tên người đánh giá",
  "search.enterTeacherName": "Nhập tên giáo viên",
  "search.enterTeacherUID": "Nhập UID giáo viên",
  "search.enterTeachingQuality": "Nhập chất lượng giảng dạy",
  "search.enterValue": "Nhập giá trị",
  "search.enterWorkload": "Nhập khối lượng công việc",
  "search.enterYear": "Nhập năm",
  "search.equals": "Bằng",
  "search.exactMatch": "Khớp chính xác",
  "search.examMethod": "Phương thức thẩm định",
  "search.filters.allCourseTypes": "Tất cả các loại",
  "search.filters.allDepartments": "Tất cả các khoa",
  "search.filters.apply": "Áp dụng bộ lọc",
  "search.filters.courseType": "Phân loại khóa học",
  "search.filters.creditsAndExam": "Tín chỉ & Thi",
  "search.filters.creditsSuffix": "Tín chỉ",
  "search.filters.reset": "Đặt lại bộ lọc",
  "search.finalExamMethod": "Phương thức đánh giá cuối kỳ",
  "search.generatedQuery": "Cú pháp truy vấn được tạo ra",
  "search.gradingMethod": "Phương thức đánh giá",
  "search.greaterEqual": "Lớn hơn hoặc bằng",
  "search.greaterThan": "Lớn hơn",
  "search.groupEnd": "Kết thúc nhóm",
  "search.groupOperator": "Toán tử nhóm",
  "search.groupStart": "Bắt đầu nhóm",
  "search.history": "Lịch sử tìm kiếm",
  "search.history.clear": "Xóa sạch",
  "search.hot": "Tìm kiếm tiêu biểu",
  "search.hot_ranking": "Xếp hạng tiêu biểu",
  "search.intentCourse": "Khóa học",
  "search.intentGeneral": "Tổng hợp",
  "search.intentReview": "Đánh giá",
  "search.intentTeacher": "Giảng viên",
  "search.intent_hint": "Đang tìm {type} liên quan...",
  "search.lessEqual": "Nhỏ hơn hoặc bằng",
  "search.lessThan": "Nhỏ hơn",
  "search.loading": "Đang tìm kiếm...",
  "search.maxCourseInterest": "Mức độ quan tâm cao nhất",
  "search.maxDifficulty": "Độ khó cao nhất",
  "search.maxRating": "Điểm số cao nhất",
  "search.maxReviewCount": "Số lượng đánh giá tối đa",
  "search.maxTeachingQuality": "Chất lượng giảng dạy cao nhất",
  "search.maxWorkload": "Khối lượng công việc tối đa",
  "search.minCourseInterest": "Mức độ quan tâm tối thiểu",
  "search.minDifficulty": "Độ khó thấp nhất",
  "search.minRating": "Điểm số tối thiểu",
  "search.minReviewCount": "Số lượng đánh giá tối thiểu",
  "search.minTeachingQuality": "Chất lượng giảng dạy tối thiểu",
  "search.minWorkload": "Khối lượng công việc tối thiểu",
  "search.moreSuggestions": "Và một đề nghị",
  "search.noResults": "Không tìm thấy kết quả liên quan",
  "search.noResults.description": "Không tìm thấy khóa học liên quan, hãy thử từ khóa khác.",
  "search.noResults.title": "Không tìm thấy kết quả",
  "search.noResultsHint": "Thử các từ khóa hoặc phạm vi tìm kiếm khác",
  "search.notContains": "Không bao gồm",
  "search.notEquals": "Không bằng",
  "search.operators.contains": "Bao gồm",
  "search.operators.endsWith": "Kết thúc bằng",
  "search.operators.equals": "Bằng",
  "search.operators.greaterThan": "Lớn hơn",
  "search.operators.greaterThanOrEqual": "Lớn hơn hoặc bằng",
  "search.operators.lessThan": "Nhỏ hơn",
  "search.operators.lessThanOrEqual": "Nhỏ hơn hoặc bằng",
  "search.operators.notContains": "Không bao gồm",
  "search.operators.notEquals": "Không bằng",
  "search.operators.startsWith": "Bắt đầu bằng",
  "search.or": "Hoặc",
  "search.orExample": "A hoặc B",
  "search.orExplanation": "A hoặc B thỏa mãn một trong số đó",
  "search.overallRating": "Đánh giá tổng thể",
  "search.parenthesesExample": "(A và B) Hoặc C",
  "search.parenthesesExample2": "A và (B hoặc C)",
  "search.parenthesesExplanation": "Cả A và B đều thỏa mãn, hoặc C thỏa mãn",
  "search.parenthesesExplanation2": "A phải đáp ứng và B hoặc C phải đáp ứng một trong số đó",
  "search.placeholder": "Tìm kiếm khóa học, giáo viên hoặc từ khóa…",
  "search.placeholder.courseNameTeacherCode": "Nhập tên khóa học, giáo viên hoặc mã khóa học…",
  "search.prerequisites": "Học phần tiên quyết",
  "search.professor": "Giảng viên",
  "search.queryBuilder": "Trình tạo truy vấn",
  "search.querySyntaxCopied": "Cú pháp truy vấn đã được sao chép vào bảng tạm",
  "search.rating": "Điểm số",
  "search.recent": "Tìm kiếm gần đây",
  "search.refresh": "Làm mới",
  "search.reviewCount": "Số lượng đánh giá",
  "search.reviewFilters": "Lọc đánh giá",
  "search.reviewerName": "Tên người đánh giá",
  "search.scope": "Phạm vi tìm kiếm",
  "search.scopeAll": "Tất cả",
  "search.scopeCourses": "Khóa học",
  "search.scopeReviews": "Bình luận",
  "search.scopeTeachers": "Giáo viên",
  "search.search": "Tìm kiếm",
  "search.searchResults": "Kết quả tìm kiếm: {count}",
  "search.selectCourseAttribute": "Chọn thuộc tính khóa học",
  "search.selectCourseType": "Chọn loại khóa học",
  "search.selectCredits": "Chọn tín chỉ",
  "search.selectDepartment": "Chọn khoa",
  "search.selectElectiveField": "Chọn lĩnh vực tự chọn",
  "search.selectExamMethod": "Chọn phương thức đánh giá",
  "search.selectField": "Chọn trường",
  "search.selectOperator": "Chọn toán tử",
  "search.selectSemester": "Chọn học kỳ",
  "search.semester": "Học kỳ",
  "search.simple": "Đơn giản",
  "search.simpleSearch": "Tìm kiếm đơn giản",
  "search.startsWith": "Bắt đầu bằng",
  "search.subtitle": "Tìm khóa học mà bạn quan tâm",
  "search.switchToAdvanced": "Chuyển sang lọc nâng cao",
  "search.switchToBuilder": "Chuyển sang Query Builder",
  "search.switchToSimple": "Chuyển sang tìm kiếm đơn giản",
  "search.syntaxExplanation": "Giới thiệu về ngữ pháp",
  "search.teacherFilters": "Giáo viên sàng lọc",
  "search.teacherName": "Tên của giáo viên",
  "search.teacherUID": "Giáo viên UID",
  "search.teachingQuality": "chất lượng giảng dạy",
  "search.title": "Kết quả tìm kiếm",
  "search.workload": "khối lượng công việc",
  "search.year": "năm / năm / năm",
  "semester.academicYear": "Năm học",
  "semester.autumn": "Học kỳ Thu",
  "semester.spring": "Học kỳ Xuân",
  "semester.summer": "Học kỳ Hè",
  "settings.about": "Về chúng tôi",
  "settings.algorithmStandard": "Bảng màu tiêu chuẩn (MD3 Native)",
  "settings.api.fail": "Không thể kết nối API Core, hãy kiểm tra trạng thái backend",
  "settings.api.success": "Kết nối API Core OK",
  "settings.apiMgmt": "Quản lý nút API",
  "settings.apiMgmtDesc": "Chọn backend dữ liệu khác nhau để có kết nối tốt nhất. Hỗ trợ định tuyến tự động bộ nhớ đệm cạnh.",
  "settings.appLanguage": "Ngôn ngữ ứng dụng",
  "settings.appearance": "Giao diện",
  "settings.appearance.language": "Điều khiển ngôn ngữ",
  "settings.appearance.theme": "Chế độ hiển thị",
  "settings.appearance.theme.dark": "Chế độ tối",
  "settings.appearance.theme.light": "Chế độ sáng",
  "settings.appearance.theme.system": "Mặc định hệ thống",
  "settings.appearance.title": "Chủ đề & Giao diện",
  "settings.brandColor": "Màu thương hiệu",
  "settings.brandColorDesc": "Chọn một màu hạt giống để tạo động chủ đề MD3 cho toàn trang.",
  "settings.cache.cleared": "Đã xóa thành công tất cả dữ liệu ngoại tuyến",
  "settings.clearHistory": "Xóa lịch sử tìm kiếm",
  "settings.colorAlgorithm": "Thuật toán tạo màu",
  "settings.colorAlgorithmDesc": "Kiểm soát độ sống động và biểu cảm của màu sắc. Hỗ trợ M3 Tonal Spot tiêu chuẩn.",
  "settings.colors.blue": "Xanh cổ điển",
  "settings.colors.emerald": "Xanh ngọc lục bảo",
  "settings.colors.lavender": "Oải hương",
  "settings.colors.neutral": "Xám trung tính",
  "settings.colors.pink": "Hồng Anh Đào",
  "settings.colors.purple": "Tím Oải hương",
  "settings.colors.slate": "Xám phiến đá",
  "settings.colors.teal": "Xanh mòng két",
  "settings.confirmClearHistory": "Bạn có chắc muốn xóa tất cả lịch sử tìm kiếm không?",
  "settings.development": "Tùy chọn nhà phát triển",
  "settings.development.desc": "Cài đặt gỡ lỗi.",
  "settings.diagnostic.title": "Truy vết & Chẩn đoán",
  "settings.edgeCache": "Bộ nhớ đệm cạnh (Cloudflare)",
  "settings.edgeCacheDisabled": "Tăng tốc cạnh chưa được bật",
  "settings.edgeCacheEnabled": "Được tăng tốc qua Cloudflare Worker & Edge Caching",
  "settings.hideDevtools": "Ẩn Devtools",
  "settings.hideDevtools.desc": "Ẩn Vue Devtools.",
  "settings.historyCount": "Hiện có {count} bản ghi trên thiết bị này",
  "settings.historyLimit": "Giới hạn lịch sử",
  "settings.language": "Ngôn ngữ ứng dụng",
  "settings.maintenance": "Quản lý & Bảo trì",
  "settings.network.title": "Mạng & Cạnh",
  "settings.offlineMode": "Chế độ ngoại tuyến",
  "settings.privacy": "Quyền riêng tư & Tìm kiếm",
  "settings.searchHistory": "Lưu lịch sử tìm kiếm",
  "settings.searchHistoryDesc": "Giữ các từ khóa tìm kiếm tại chỗ để truy cập nhanh",
  "settings.settings": "Cài đặt",
  "settings.subtitle": "Tùy chọn cấu hình ứng dụng và gỡ lỗi chẩn đoán",
  "settings.system.title": "Thông tin hệ thống",
  "settings.theme": "Chủ đề & Giao diện",
  "settings.themeMode": "Chế độ chủ đề",
  "settings.title": "Cài đặt",
  "teacher.detail.basic": "Hồ sơ giảng viên",
  "teacher.detail.courses": "Các khóa học hiện tại",
  "teacher.detail.dept": "Đơn vị công tác",
  "teacher.detail.deptPlaceholder": "Không rõ đơn vị",
  "teacher.detail.name": "Họ và tên",
  "teacher.detail.noCourses": "Không tìm thấy khóa học",
  "teacher.detail.noCoursesNotice": "Không có buổi giảng dạy tích cực nào được ghi lại.",
  "teacher.detail.radar": "Radar phong cách giảng dạy",
  "teacher.detail.reviews": "Tổng đánh giá",
  "teacherDetail": "chi tiết về giáo viên",
  "teacherDetail.basedOnReviews": "Dựa trên đánh giá {n}",
  "teacherDetail.creationTime": "Thời gian tạo ra",
  "teacherDetail.difficultRating": "Đánh giá khó khăn",
  "teacherDetail.easyRating": "Đơn giản đánh giá",
  "teacherDetail.multiDimensionalRating": "Giáo viên đánh giá nhiều chiều",
  "teacherDetail.teacherId": "Giáo viên ID",
  "teacherDetail.updateTime": "Thời gian cập nhật",
  "teacherDetail.writeReview": "viết đánh giá",
  "teachers.course": "khóa học / khóa học",
  "teachers.courseDifficulty": "độ khó của khóa học",
  "teachers.courseInterest": "mức độ hứng thú của khóa học",
  "teachers.courses": "khóa học / khóa học",
  "teachers.detail": "chi tiết về giáo viên",
  "teachers.fetchError": "Lấy danh sách giáo viên không thành công",
  "teachers.homeworkLoad": "khối lượng công việc / khối lượng công việc",
  "teachers.noReviews": "tạm thời không có đánh giá",
  "teachers.noReviewsDesc": "Chưa có đánh giá nào về giáo viên này",
  "teachers.relatedCourses": "Các khóa học liên quan",
  "teachers.review": "đánh giá / đánh giá / đánh giá",
  "teachers.reviews": "đánh giá / đánh giá / đánh giá",
  "teachers.teacherReviews": "Đánh giá của giáo viên",
  "teachers.teachingCourses": "các khóa học giảng dạy",
  "teachers.teachingQuality": "chất lượng giảng dạy",
  "teachers.title": "Danh sách các giáo viên",
  "teachers.viewAllCourses": "Xem tất cả các khóa học",
  "teachers.viewAllReviews": "Xem tất cả các đánh giá",
  "theme.auto": "Tự động (tự động)",
  "theme.dark": "màu tối",
  "theme.light": "màu sáng / ánh sáng",
  "user.accessToken": "Token truy cập",
  "user.clearToken": "Xóa Token",
  "user.count": "Số lượng",
  "user.dashboard": "Bảng điều khiển",
  "user.followedTeachers": "Giảng viên đã theo dõi",
  "user.identityAndAccess": "Danh tính & Truy cập",
  "user.kpi": "Chỉ số KPI",
  "user.onlyHighRating": "Chỉ hiện đánh giá xếp hạng cao",
  "user.preferences": "Tùy chọn",
  "user.preferredDepartment": "Khoa/Viện ưa thích",
  "user.profileBio": "Tiểu sử",
  "user.profileName": "Tên hồ sơ",
  "user.ratingRange": "Đánh giá (1-5)",
  "user.recentReviews": "Đánh giá gần đây",
  "user.refreshData": "Làm mới dữ liệu",
  "user.savePreferences": "Lưu tùy chọn",
  "user.saveToken": "Lưu Token",
  "user.savedCourses": "Khóa học đã lưu",
  "user.section": "Phần",
  "user.submitReview": "Gửi đánh giá",
  "user.userCenter": "Trung tâm người dùng",
  "userCenter.dashboard": "仪表盘",
  "userCenter.description": "WHU.sb 用户中心 — 管理个人信息、收藏和评价",
  "userCenter.favorites": "Yêu thích",
  "userCenter.logout": "退出登录",
  "userCenter.profile": "个人信息",
  "userCenter.reviews": "Đánh giá của tôi",
  "userCenter.settings": "Cài đặt",
  "userCenter.title": "用户中心",
  "userCenter.titleTemplate": "%s | 用户中心",
  "utilities.subtitle": "Bộ sưu tập các công cụ và trang web phổ biến",
  "utilities.title": "công cụ thực tế",
  "validation.maxLength": "Cho phép tối đa {max} ký tự",
  "validation.minLength": "Cần tối thiểu {min} ký tự",
  "wasm.browsers.chrome": "Chrome"
}
